selectfiles/__init__.py
selectfiles/plugin.py
mkdocs_select_files-0.4.0.dist-info/LICENSE
mkdocs_select_files-0.4.0.dist-info/METADATA
mkdocs_select_files-0.4.0.dist-info/WHEEL
mkdocs_select_files-0.4.0.dist-info/entry_points.txt
mkdocs_select_files-0.4.0.dist-info/top_level.txt
mkdocs_select_files-0.4.0.dist-info/RECORD
