Metadata-Version: 2.1
Name: mkdocs-select-files
Version: 0.4.0
Summary: Filter pages for assignments
Home-page: https://github.com/supcik/mkdocs-select-files
Author: Jacques Supcik
Author-email: jacques@supcik.net
License: Apache-2.0
Platform: UNKNOWN
Requires-Dist: mkdocs
